drf_nested_decorator/__init__.py
drf_nested_decorator/decorator.py
drf_nested_decorator/routers.py
drf_nested_decorator/tests.py
drf_nested_decorator-0.5.dist-info/DESCRIPTION.rst
drf_nested_decorator-0.5.dist-info/METADATA
drf_nested_decorator-0.5.dist-info/RECORD
drf_nested_decorator-0.5.dist-info/WHEEL
drf_nested_decorator-0.5.dist-info/metadata.json
drf_nested_decorator-0.5.dist-info/top_level.txt
