Metadata-Version: 2.0
Name: drf-nested-decorator
Version: 0.5
Summary: An extra decorator for Django Rest Framework that allows methods of a viewset to accept a nested key.
Home-page: https://github.com/luminum-solutions/drf-nested-decorator
Author: Zowie Langdon
Author-email: zowie@akoten.com
License: MIT
Platform: UNKNOWN
Classifier: Intended Audience :: Developers
Classifier: Programming Language :: Python
Classifier: Programming Language :: Python :: 3.3
Requires-Dist: djangorestframework (>=3.1.3)
